retinalysis_inference-0.5.0.dist-info/licenses/LICENSE
rtnls_inference/__init__.py
rtnls_inference/metrics.py
rtnls_inference/utils.py
rtnls_inference/datasets/__init__.py
rtnls_inference/datasets/base.py
rtnls_inference/datasets/fundus.py
rtnls_inference/ensembles/__init__.py
rtnls_inference/ensembles/base.py
rtnls_inference/ensembles/ensemble_classification.py
rtnls_inference/ensembles/ensemble_heatmap_regression.py
rtnls_inference/ensembles/ensemble_keypoints.py
rtnls_inference/ensembles/ensemble_regression.py
rtnls_inference/ensembles/ensemble_segmentation.py
rtnls_inference/ensembles/ensemble_segmentation_overlaps.py
rtnls_inference/ensembles/utils.py
rtnls_inference/transforms/__init__.py
rtnls_inference/transforms/base.py
rtnls_inference/transforms/basic.py
rtnls_inference/transforms/fundus.py
retinalysis_inference-0.5.0.dist-info/METADATA
retinalysis_inference-0.5.0.dist-info/WHEEL
retinalysis_inference-0.5.0.dist-info/top_level.txt
retinalysis_inference-0.5.0.dist-info/RECORD
