Metadata-Version: 2.4
Name: retinalysis-inference
Version: 0.5.0
Summary: Retinal model inference package
Author-email: Jose Vargas <j.vargasquiros@erasmusmc.nl>
License:                     GNU AFFERO GENERAL PUBLIC LICENSE
Project-URL: Homepage, https://github.com/Eyened/retinalysis-inference
Project-URL: Bug Tracker, https://github.com/Eyened/retinalysis-inference/issues
Requires-Python: <3.13,>=3.10
License-File: LICENSE
Requires-Dist: numpy==2.*
Requires-Dist: pandas==2.*
Requires-Dist: opencv-python==4.*
Requires-Dist: joblib==1.*
Requires-Dist: Pillow==11.*
Requires-Dist: click==8.*
Requires-Dist: pydicom==3.*
Requires-Dist: nbstripout==0.3.9
Requires-Dist: lightning==2.*
Requires-Dist: albumentations==1.3.1
Requires-Dist: PyYAML>=5.4
Requires-Dist: monai==1.5.1
Requires-Dist: huggingface-hub==0.25.1
Requires-Dist: GPUtil==1.*
Dynamic: license-file
